SuSMoST_Monte_Carlo.libs/libopen-pal-4e447685.so.13.0.4
SuSMoST_Monte_Carlo.libs/libopen-rte-433d319d.so.12.0.4
SuSMoST_Monte_Carlo.libs/libnuma-428e8baf.so.1.0.0
SuSMoST_Monte_Carlo.libs/libhwloc-8a7ce5b6.so.5.7.5
SuSMoST_Monte_Carlo.libs/libmpi-14335c9d.so.12.0.7
SuSMoST_Monte_Carlo.libs/libltdl-3a30a669.so.7
SuSMoST_Monte_Carlo.libs/libmpi_cxx-842cb374.so.1.1.3
susmost/mc/mc.py
susmost/mc/tmatrix.cpython-38-x86_64-linux-gnu.so
susmost/mc/metropolis.so
susmost/mc/__init__.py
SuSMoST_Monte_Carlo-1.2.19.dist-info/WHEEL
SuSMoST_Monte_Carlo-1.2.19.dist-info/top_level.txt
SuSMoST_Monte_Carlo-1.2.19.dist-info/RECORD
SuSMoST_Monte_Carlo-1.2.19.dist-info/METADATA
