Metadata-Version: 2.1
Name: SuSMoST-Monte-Carlo
Version: 1.2.19
Summary: SUrface Science MOdeling and Simulation Toolkit: Monte Carlo package
Home-page: https://susmost.com
Requires-Dist: numpy >=1.13.0
Requires-Dist: mpi4py >=2.0.0
Requires-Dist: GitPython
